README.md
setup.py
conan/__init__.py
conan/conan_promote.py
conan/main.py
conan/requirements.txt
conan/requirements_dev.txt
conan/test/__init__.py
conan/test/promote_test.py
conan_promote.egg-info/PKG-INFO
conan_promote.egg-info/SOURCES.txt
conan_promote.egg-info/dependency_links.txt
conan_promote.egg-info/entry_points.txt
conan_promote.egg-info/requires.txt
conan_promote.egg-info/top_level.txt